pragyan/__init__.py
pragyan/algorithm_visualizers.py
pragyan/animations.py
pragyan/cli.py
pragyan/llm_client.py
pragyan/logger.py
pragyan/main.py
pragyan/models.py
pragyan/py.typed
pragyan/scraper.py
pragyan/solver.py
pragyan/utils.py
pragyan/video_generator.py
pragyan/video_generator_backup.py
pragyan-1.1.2.dist-info/licenses/LICENSE
pragyan-1.1.2.dist-info/METADATA
pragyan-1.1.2.dist-info/WHEEL
pragyan-1.1.2.dist-info/entry_points.txt
pragyan-1.1.2.dist-info/top_level.txt
pragyan-1.1.2.dist-info/RECORD
