Metadata-Version: 2.4
Name: pragyan
Version: 1.1.2
Summary: AI-powered DSA question solver with video explanations using Manim animations
Author-email: Kamal <kamal@example.com>
License-Expression: MIT
Project-URL: Homepage, https://github.com/Kamalllx/pragyan_pypi
Project-URL: Documentation, https://github.com/Kamalllx/pragyan_pypi#readme
Project-URL: Repository, https://github.com/Kamalllx/pragyan_pypi
Project-URL: Issues, https://github.com/Kamalllx/pragyan_pypi/issues
Keywords: dsa,leetcode,algorithms,data-structures,ai,video-generation,manim,education
Classifier: Development Status :: 4 - Beta
Classifier: Intended Audience :: Developers
Classifier: Intended Audience :: Education
Classifier: Operating System :: OS Independent
Classifier: Programming Language :: Python :: 3
Classifier: Programming Language :: Python :: 3.9
Classifier: Programming Language :: Python :: 3.10
Classifier: Programming Language :: Python :: 3.11
Classifier: Programming Language :: Python :: 3.12
Classifier: Topic :: Education
Classifier: Topic :: Scientific/Engineering :: Artificial Intelligence
Requires-Python: >=3.9
License-File: LICENSE
Requires-Dist: google-generativeai>=0.3.0
Requires-Dist: groq>=0.4.0
Requires-Dist: langchain>=0.1.0
Requires-Dist: langchain-community>=0.0.10
Requires-Dist: beautifulsoup4>=4.12.0
Requires-Dist: requests>=2.31.0
Requires-Dist: selenium>=4.15.0
Requires-Dist: webdriver-manager>=4.0.0
Requires-Dist: manim>=0.18.0
Requires-Dist: moviepy>=1.0.3
Requires-Dist: Pillow>=10.0.0
Requires-Dist: numpy>=1.24.0
Requires-Dist: click>=8.1.0
Requires-Dist: rich>=13.0.0
Requires-Dist: pydantic>=2.0.0
Requires-Dist: python-dotenv>=1.0.0
Provides-Extra: dev
Requires-Dist: pytest>=7.0.0; extra == "dev"
Requires-Dist: pytest-cov>=4.0.0; extra == "dev"
Requires-Dist: black>=23.0.0; extra == "dev"
Requires-Dist: isort>=5.12.0; extra == "dev"
Requires-Dist: mypy>=1.0.0; extra == "dev"
Dynamic: license-file
